odoo/addons/project_stage_mgmt/README.rst
odoo/addons/project_stage_mgmt/__init__.py
odoo/addons/project_stage_mgmt/__manifest__.py
odoo/addons/project_stage_mgmt/i18n/it.po
odoo/addons/project_stage_mgmt/i18n/project_stage_mgmt.pot
odoo/addons/project_stage_mgmt/readme/CONTRIBUTORS.rst
odoo/addons/project_stage_mgmt/readme/DESCRIPTION.rst
odoo/addons/project_stage_mgmt/static/description/icon.png
odoo/addons/project_stage_mgmt/static/description/index.html
odoo/addons/project_stage_mgmt/views/project.xml
odoo_addon_project_stage_mgmt-15.0.1.0.0.4.dist-info/METADATA
odoo_addon_project_stage_mgmt-15.0.1.0.0.4.dist-info/WHEEL
odoo_addon_project_stage_mgmt-15.0.1.0.0.4.dist-info/top_level.txt
odoo_addon_project_stage_mgmt-15.0.1.0.0.4.dist-info/RECORD
